<?xml version="1.0" encoding="utf-8"?>
<Actions>
  <Action type="None" description="Default Actions">
	  <FiredBy type="Accelerometer" direction="LeftMove" />
	  <FiredBy type="Accelerometer" direction="RightMove" />
	  <FiredBy type="Accelerometer" direction="FwdMove" />
	  <FiredBy type="Accelerometer" direction="BackMove" />
	  <FiredBy type="WiimoteButtons" button="Up" />
	  <FiredBy type="WiimoteButtons" button="Down" />
	  <FiredBy type="WiimoteButtons" button="Left" />
	  <FiredBy type="WiimoteButtons" button="Right" />
	  <FiredBy type="WiimoteButtons" button="A" />
	  <FiredBy type="WiimoteButtons" button="B" />
	  <FiredBy type="WiimoteButtons" button="Plus" />
	  <FiredBy type="WiimoteButtons" button="Home" />
	  <FiredBy type="WiimoteButtons" button="Minus" />
	  <FiredBy type="WiimoteButtons" button="One" />
	  <FiredBy type="WiimoteButtons" button="Two" />
  </Action>
</Actions>